LICENSE
README.md
setup.py
src/matrixpy.py
src/matrix_py.egg-info/PKG-INFO
src/matrix_py.egg-info/SOURCES.txt
src/matrix_py.egg-info/dependency_links.txt
src/matrix_py.egg-info/entry_points.txt
src/matrix_py.egg-info/requires.txt
src/matrix_py.egg-info/top_level.txt
src/matrix_py.egg-info/zip-safe